pythesint/__init__.py
pythesint/cf_vocabulary.py
pythesint/gcmd_vocabulary.py
pythesint/iso19115_vocabulary.py
pythesint/json_vocabulary.py
pythesint/mmd_vocabulary.py
pythesint/pathsolver.py
pythesint/pythesint.py
pythesint/pythesintrc.yaml
pythesint/utils.py
pythesint/vocabulary.py
pythesint/wkv_vocabulary.py
pythesint/basedata/cf_standard_name
pythesint/basedata/gcmd_horizontalresolutionrange
pythesint/basedata/gcmd_instrument
pythesint/basedata/gcmd_location
pythesint/basedata/gcmd_platform
pythesint/basedata/gcmd_project
pythesint/basedata/gcmd_provider
pythesint/basedata/gcmd_rucontenttype
pythesint/basedata/gcmd_science_keyword
pythesint/basedata/gcmd_temporalresolutionrange
pythesint/basedata/gcmd_verticalresolutionrange
pythesint/basedata/wkv_variable
pythesint/tests/__init__.py
pythesint/tests/test_cf_vocabulary.py
pythesint/tests/test_gcmd_vocabulary.py
pythesint/tests/test_json_vocabulary.py
pythesint/tests/test_mmd_vocabulary.py
pythesint/tests/test_pythesint.py
pythesint/tests/test_vocabulary.py
pythesint/tests/test_wkv_vocabulary.py
pythesint-1.7.2.dist-info/licenses/LICENSE
pythesint-1.7.2.dist-info/METADATA
pythesint-1.7.2.dist-info/WHEEL
pythesint-1.7.2.dist-info/top_level.txt
pythesint-1.7.2.dist-info/RECORD
