Metadata-Version: 2.4
Name: pythesint
Version: 1.7.2
Summary: A Python interface to various metadata vocabularies
Author: Morten W. Hansen, Aleksander Vines
Author-email: "Anton A. Korosov" <anton.korosov@nersc.no>
License:                     GNU GENERAL PUBLIC LICENSE
Project-URL: Repository, https://github.com/nansencenter/py-thesaurus-interface
Keywords: metadata,standards,thesaurus,vocabulary
Classifier: Development Status :: 5 - Production/Stable
Classifier: Environment :: Plugins
Classifier: Environment :: Console
Classifier: Intended Audience :: Information Technology
Classifier: Intended Audience :: Science/Research
Classifier: License :: OSI Approved :: GNU General Public License v3 (GPLv3)
Classifier: Natural Language :: English
Classifier: Operating System :: OS Independent
Classifier: Programming Language :: Python
Classifier: Topic :: Scientific/Engineering
Classifier: Topic :: Scientific/Engineering :: Atmospheric Science
Classifier: Topic :: Scientific/Engineering :: Information Analysis
Classifier: Topic :: Utilities
License-File: LICENSE
Requires-Dist: PyYAML
Requires-Dist: rapidfuzz
Requires-Dist: requests
Requires-Dist: xdg; platform_system != "Windows"
Dynamic: license-file
